Workbook

Sheet Data Entry
A1: Department | B1: Indicator | C1: Target | D1: Goal | E1: Definition/Formula | F1: Frequency | G1: Responsible | H1: Jan | I1: Feb | J1: Mar | K1: Q1 Avg | L1: Status | M1: Notes
A2: Marketing | B2: Brand reach | C2: 5000 | D2: Higher | E2: Total social media engagements + website visits per month | F2: Monthly | K2: =AVERAGE(H2:J2) | L2: =IF(OR(K2='',C2=''),'',IF(D2='Higher',IF(K2>=C2,'On Target','Below Target'),IF(K2<=C2,'On Target','Below Target')))
A3: Marketing | B3: Lead conversion rate | C3: 0.1 | D3: Higher | E3: Number of inquiries converted to applications ÷ total inquiries | F3: Monthly | K3: =AVERAGE(H3:J3) | L3: =IF(OR(K3='',C3=''),'',IF(D3='Higher',IF(K3>=C3,'On Target','Below Target'),IF(K3<=C3,'On Target','Below Target')))
A4: Marketing | B4: Event turnout | C4: 0.75 | D4: Higher | E4: Attendance at career fairs/open days ÷ target attendance | F4: Monthly | K4: =AVERAGE(H4:J4) | L4: =IF(OR(K4='',C4=''),'',IF(D4='Higher',IF(K4>=C4,'On Target','Below Target'),IF(K4<=C4,'On Target','Below Target')))
A5: Marketing | B5: Cost per lead | C5: 50 | D5: Lower | E5: Marketing spend ÷ # of new inquiries | F5: Monthly | K5: =AVERAGE(H5:J5) | L5: =IF(OR(K5='',C5=''),'',IF(D5='Higher',IF(K5>=C5,'On Target','Below Target'),IF(K5<=C5,'On Target','Below Target')))
A6: Admissions | B6: Application-to-enrollment rate | C6: 0.6 | D6: Higher | E6: Enrolled applicants ÷ total applications | F6: Monthly | K6: =AVERAGE(H6:J6) | L6: =IF(OR(K6='',C6=''),'',IF(D6='Higher',IF(K6>=C6,'On Target','Below Target'),IF(K6<=C6,'On Target','Below Target')))
A7: Admissions | B7: Program fill rate | C7: 0.9 | D7: Higher | E7: Filled program slots ÷ total available slots | F7: Monthly | K7: =AVERAGE(H7:J7) | L7: =IF(OR(K7='',C7=''),'',IF(D7='Higher',IF(K7>=C7,'On Target','Below Target'),IF(K7<=C7,'On Target','Below Target')))
A8: Admissions | B8: Yield rate | C8: 0.75 | D8: Higher | E8: Accepted students who register ÷ total offers issued | F8: Monthly | K8: =AVERAGE(H8:J8) | L8: =IF(OR(K8='',C8=''),'',IF(D8='Higher',IF(K8>=C8,'On Target','Below Target'),IF(K8<=C8,'On Target','Below Target')))
A9: Admissions | B9: Processing time | C9: 14 | D9: Lower | E9: Average days from application submission to admission decision | F9: Monthly | K9: =AVERAGE(H9:J9) | L9: =IF(OR(K9='',C9=''),'',IF(D9='Higher',IF(K9>=C9,'On Target','Below Target'),IF(K9<=C9,'On Target','Below Target')))
A10: Exams | B10: Exam completion rate | C10: 0.98 | D10: Higher | E10: Registered students who sit exams ÷ total registered | F10: Monthly | K10: =AVERAGE(H10:J10) | L10: =IF(OR(K10='',C10=''),'',IF(D10='Higher',IF(K10>=C10,'On Target','Below Target'),IF(K10<=C10,'On Target','Below Target')))
A11: Exams | B11: Results turnaround time | C11: 21 | D11: Lower | E11: Days from exam administration to published results | F11: Monthly | K11: =AVERAGE(H11:J11) | L11: =IF(OR(K11='',C11=''),'',IF(D11='Higher',IF(K11>=C11,'On Target','Below Target'),IF(K11<=C11,'On Target','Below Target')))
A12: Exams | B12: Malpractice rate | C12: 0.005 | D12: Lower | E12: Confirmed malpractice cases ÷ total exam candidates | F12: Monthly | K12: =AVERAGE(H12:J12) | L12: =IF(OR(K12='',C12=''),'',IF(D12='Higher',IF(K12>=C12,'On Target','Below Target'),IF(K12<=C12,'On Target','Below Target')))
A13: Exams | B13: Appeal rate | C13: 0.02 | D13: Lower | E13: Exam appeals lodged ÷ students examined | F13: Monthly | K13: =AVERAGE(H13:J13) | L13: =IF(OR(K13='',C13=''),'',IF(D13='Higher',IF(K13>=C13,'On Target','Below Target'),IF(K13<=C13,'On Target','Below Target')))
... A85: Research & Innovation | B85: Innovation training completion | C85: 0.9 | D85: Higher | E85: Participants completing innovation workshops ÷ enrolled participants | F85: Annual | K85: =AVERAGE(H85:J85) | L85: =IF(OR(K85='',C85=''),'',IF(D85='Higher',IF(K85>=C85,'On Target','Below Target'),IF(K85<=C85,'On Target','Below Target')))

Sheet Summary Dashboard
A1: Department | B1: KPI Count | C1: On Target | D1: Below Target | E1: % On Target | F1: Notes
A2: Marketing | B2: =COUNTIF('Data Entry'!A:A,A2) | C2: =COUNTIFS('Data Entry'!A:A,A2,'Data Entry'!L:L,"On Target") | D2: =COUNTIFS('Data Entry'!A:A,A2,'Data Entry'!L:L,"Below Target") | E2: =IF(B2=0,'',C2/B2)
A3: Admissions | B3: =COUNTIF('Data Entry'!A:A,A3) | C3: =COUNTIFS('Data Entry'!A:A,A3,'Data Entry'!L:L,"On Target") | D3: =COUNTIFS('Data Entry'!A:A,A3,'Data Entry'!L:L,"Below Target") | E3: =IF(B3=0,'',C3/B3)
A4: Exams | B4: =COUNTIF('Data Entry'!A:A,A4) | C4: =COUNTIFS('Data Entry'!A:A,A4,'Data Entry'!L:L,"On Target") | D4: =COUNTIFS('Data Entry'!A:A,A4,'Data Entry'!L:L,"Below Target") | E4: =IF(B4=0,'',C4/B4)
A5: Transportation | B5: =COUNTIF('Data Entry'!A:A,A5) | C5: =COUNTIFS('Data Entry'!A:A,A5,'Data Entry'!L:L,"On Target") | D5: =COUNTIFS('Data Entry'!A:A,A5,'Data Entry'!L:L,"Below Target") | E5: =IF(B5=0,'',C5/B5)
A6: Rock Farm | B6: =COUNTIF('Data Entry'!A:A,A6) | C6: =COUNTIFS('Data Entry'!A:A,A6,'Data Entry'!L:L,"On Target") | D6: =COUNTIFS('Data Entry'!A:A,A6,'Data Entry'!L:L,"Below Target") | E6: =IF(B6=0,'',C6/B6)
A7: Skills - Short Courses | B7: =COUNTIF('Data Entry'!A:A,A7) | C7: =COUNTIFS('Data Entry'!A:A,A7,'Data Entry'!L:L,"On Target") | D7: =COUNTIFS('Data Entry'!A:A,A7,'Data Entry'!L:L,"Below Target") | E7: =IF(B7=0,'',C7/B7)
A8: School of Health Sciences | B8: =COUNTIF('Data Entry'!A:A,A8) | C8: =COUNTIFS('Data Entry'!A:A,A8,'Data Entry'!L:L,"On Target") | D8: =COUNTIFS('Data Entry'!A:A,A8,'Data Entry'!L:L,"Below Target") | E8: =IF(B8=0,'',C8/B8)
A9: Human Resource | B9: =COUNTIF('Data Entry'!A:A,A9) | C9: =COUNTIFS('Data Entry'!A:A,A9,'Data Entry'!L:L,"On Target") | D9: =COUNTIFS('Data Entry'!A:A,A9,'Data Entry'!L:L,"Below Target") | E9: =IF(B9=0,'',C9/B9)
A10: Legal | B10: =COUNTIF('Data Entry'!A:A,A10) | C10: =COUNTIFS('Data Entry'!A:A,A10,'Data Entry'!L:L,"On Target") | D10: =COUNTIFS('Data Entry'!A:A,A10,'Data Entry'!L:L,"Below Target") | E10: =IF(B10=0,'',C10/B10)
A11: Library | B11: =COUNTIF('Data Entry'!A:A,A11) | C11: =COUNTIFS('Data Entry'!A:A,A11,'Data Entry'!L:L,"On Target") | D11: =COUNTIFS('Data Entry'!A:A,A11,'Data Entry'!L:L,"Below Target") | E11: =IF(B11=0,'',C11/B11)
A12: Accounts | B12: =COUNTIF('Data Entry'!A:A,A12) | C12: =COUNTIFS('Data Entry'!A:A,A12,'Data Entry'!L:L,"On Target") | D12: =COUNTIFS('Data Entry'!A:A,A12,'Data Entry'!L:L,"Below Target") | E12: =IF(B12=0,'',C12/B12)
A13: School of Business and Humanities | B13: =COUNTIF('Data Entry'!A:A,A13) | C13: =COUNTIFS('Data Entry'!A:A,A13,'Data Entry'!L:L,"On Target") | D13: =COUNTIFS('Data Entry'!A:A,A13,'Data Entry'!L:L,"Below Target") | E13: =IF(B13=0,'',C13/B13)
... A22: Research & Innovation | B22: =COUNTIF('Data Entry'!A:A,A22) | C22: =COUNTIFS('Data Entry'!A:A,A22,'Data Entry'!L:L,"On Target") | D22: =COUNTIFS('Data Entry'!A:A,A22,'Data Entry'!L:L,"Below Target") | E22: =IF(B22=0,'',C22/B22)
